README.md
setup.py
pseudolm.egg-info/PKG-INFO
pseudolm.egg-info/SOURCES.txt
pseudolm.egg-info/dependency_links.txt
pseudolm.egg-info/requires.txt
pseudolm.egg-info/top_level.txt
pyplm/__init__.py
pyplm/models.py
pyplm/pipeline.py
pyplm/inference/__init__.py
pyplm/inference/firthlogreg.py
pyplm/inference/plmcorrection.py
pyplm/inference/plmfirthcor.py
pyplm/inference/pseudolikelihoodmax.py
pyplm/simulate/__init__.py
pyplm/simulate/basemc.py
pyplm/simulate/parallelmc.py
pyplm/simulate/sweep.py
pyplm/utilities/__init__.py
pyplm/utilities/hdf5io.py
pyplm/utilities/metadataio.py
pyplm/utilities/subsampling.py
pyplm/utilities/tools.py