Metadata-Version: 2.1
Name: pseudolm
Version: 1.0.1
Summary: Python package to perfrom psuedo-likelihood maximisation inference on Ising models
Home-page: UNKNOWN
License: UNKNOWN
Platform: UNKNOWN
Classifier: Topic :: Scientific/Engineering :: Physics
